{
	"name": "PL_XEAC_V2_MLT_HIST",
	"properties": {
		"activities": [
			{
				"name": "PL_XEAC_V2_ODS_MLT",
				"type": "ExecutePipeline",
				"dependsOn": [],
				"userProperties": [],
				"typeProperties": {
					"pipeline": {
						"referenceName": "PL_XEAC_V2_ODS_MLT",
						"type": "PipelineReference"
					},
					"waitOnCompletion": true,
					"parameters": {
						"P_DATA_INI": {
							"value": "@pipeline().parameters.P_DATA_INI",
							"type": "Expression"
						},
						"P_DATA_FI": {
							"value": "@pipeline().parameters.P_DATA_FI",
							"type": "Expression"
						}
					}
				}
			},
			{
				"name": "PL_XEAC_V2_ODS_MLT_CUMPLIMENT",
				"type": "ExecutePipeline",
				"dependsOn": [
					{
						"activity": "PL_XEAC_V2_ODS_MLT",
						"dependencyConditions": [
							"Succeeded"
						]
					}
				],
				"userProperties": [],
				"typeProperties": {
					"pipeline": {
						"referenceName": "PL_XEAC_V2_ODS_MLT_CUMPLIMENT",
						"type": "PipelineReference"
					},
					"waitOnCompletion": true,
					"parameters": {
						"P_DATA_INI": {
							"value": "@pipeline().parameters.P_DATA_INI",
							"type": "Expression"
						},
						"P_DATA_FI": {
							"value": "@pipeline().parameters.P_DATA_FI",
							"type": "Expression"
						}
					}
				}
			},
			{
				"name": "PL_XEAC_V2_DM_MLT_CUMPLIMENT",
				"type": "ExecutePipeline",
				"dependsOn": [
					{
						"activity": "PL_XEAC_V2_SKG_MLT",
						"dependencyConditions": [
							"Succeeded"
						]
					}
				],
				"userProperties": [],
				"typeProperties": {
					"pipeline": {
						"referenceName": "PL_XEAC_V2_DM_MLT_CUMPLIMENT",
						"type": "PipelineReference"
					},
					"waitOnCompletion": true,
					"parameters": {
						"P_DATA_INI": {
							"value": "@pipeline().parameters.P_DATA_INI",
							"type": "Expression"
						},
						"P_DATA_FI": {
							"value": "@pipeline().parameters.P_DATA_FI",
							"type": "Expression"
						}
					}
				}
			},
			{
				"name": "PL_XEAC_V2_DM_MLT",
				"type": "ExecutePipeline",
				"dependsOn": [
					{
						"activity": "PL_XEAC_V2_DM_MLT_CUMPLIMENT",
						"dependencyConditions": [
							"Succeeded"
						]
					}
				],
				"userProperties": [],
				"typeProperties": {
					"pipeline": {
						"referenceName": "PL_XEAC_V2_DM_MLT",
						"type": "PipelineReference"
					},
					"waitOnCompletion": true,
					"parameters": {
						"P_DATA_INI": {
							"value": "@pipeline().parameters.P_DATA_INI",
							"type": "Expression"
						},
						"P_DATA_FI": {
							"value": "@pipeline().parameters.P_DATA_FI",
							"type": "Expression"
						}
					}
				}
			},
			{
				"name": "PL_XEAC_V2_SKG_MLT",
				"type": "ExecutePipeline",
				"dependsOn": [
					{
						"activity": "PL_XEAC_V2_ODS_MLT_CUMPLIMENT",
						"dependencyConditions": [
							"Succeeded"
						]
					}
				],
				"userProperties": [],
				"typeProperties": {
					"pipeline": {
						"referenceName": "PL_XEAC_V2_SKG_MLT",
						"type": "PipelineReference"
					},
					"waitOnCompletion": true
				}
			}
		],
		"parameters": {
			"P_DATA_INI": {
				"type": "string"
			},
			"P_DATA_FI": {
				"type": "string"
			}
		},
		"folder": {
			"name": "XEAC_v2/MLT"
		},
		"annotations": [],
		"lastPublishTime": "2022-01-27T09:06:20Z"
	},
	"type": "Microsoft.DataFactory/factories/pipelines"
}